neocore/BigInteger.py
neocore/Fixed8.py
neocore/KeyPair.py
neocore/UInt160.py
neocore/UInt256.py
neocore/UIntBase.py
neocore/Utils.py
neocore/__init__.py
neocore/Cryptography/Crypto.py
neocore/Cryptography/ECCurve.py
neocore/Cryptography/Helper.py
neocore/Cryptography/MerkleTree.py
neocore/Cryptography/__init__.py
neocore/IO/BinaryReader.py
neocore/IO/BinaryWriter.py
neocore/IO/Mixins.py
neocore/IO/__init__.py
neocore/bin/__init__.py
neocore/bin/cli.py
neocore-0.5.6.dist-info/LICENSE
neocore-0.5.6.dist-info/METADATA
neocore-0.5.6.dist-info/WHEEL
neocore-0.5.6.dist-info/entry_points.txt
neocore-0.5.6.dist-info/top_level.txt
neocore-0.5.6.dist-info/RECORD
