Metadata-Version: 1.2
Name: neocore
Version: 0.5.6
Summary: Core functionality of neo-python
Home-page: https://github.com/CityOfZion/neo-python-core
Author: City of Zion
Author-email: python@cityofzion.io
License: MIT license
Keywords: neocore,neo,python,node
Platform: UNKNOWN
Classifier: Development Status :: 3 - Alpha
Classifier: Intended Audience :: Developers
Classifier: License :: OSI Approved :: MIT License
Classifier: Natural Language :: English
Classifier: Programming Language :: Python :: 3
Classifier: Programming Language :: Python :: 3.5
Classifier: Programming Language :: Python :: 3.6
Requires-Python: >=3.4
